odinson/ruleutils/__init__.py
odinson/ruleutils/config.py
odinson/ruleutils/info.py
odinson/ruleutils/oracle.py
odinson/ruleutils/queryast.py
odinson/ruleutils/queryparser.py
odinson_ruleutils-0.1b0.data/scripts/example-script
odinson_ruleutils-0.1b0.data/scripts/odinson-ruleutils-rest-api
odinson_ruleutils-0.1b0.dist-info/METADATA
odinson_ruleutils-0.1b0.dist-info/WHEEL
odinson_ruleutils-0.1b0.dist-info/top_level.txt
odinson_ruleutils-0.1b0.dist-info/RECORD
