Metadata-Version: 2.1
Name: odinson-ruleutils
Version: 0.1b0
Summary: Python library to manipulate Odinson rules.
Home-page: https://github.com/clu-ling/odinson-ruleutils
Author: marcovzla and myedibleenso and BeckySharp
Author-email: gus@parsertongue.org
License: Apache 2.0
Download-URL: https://github.com/clu-ling/odinson-ruleutils/archive/v0.1-beta.zip
Keywords: nlp
Platform: UNKNOWN
Classifier: Intended Audience :: Science/Research
Classifier: Natural Language :: English
Classifier: Topic :: Scientific/Engineering :: Artificial Intelligence
Classifier: Programming Language :: Python :: 3
Requires-Python: >=3.8
Requires-Dist: pydantic (==1.8.2)
Requires-Dist: fastapi (==0.65.2)
Requires-Dist: uvicorn (==0.11.8)
Requires-Dist: pyparsing (==2.4.7)
Provides-Extra: all
Requires-Dist: pydantic (==1.8.2) ; extra == 'all'
Requires-Dist: fastapi (==0.65.2) ; extra == 'all'
Requires-Dist: uvicorn (==0.11.8) ; extra == 'all'
Requires-Dist: pyparsing (==2.4.7) ; extra == 'all'
Requires-Dist: green (>=2.5.0) ; extra == 'all'
Requires-Dist: coverage ; extra == 'all'
Requires-Dist: mypy ; extra == 'all'
Requires-Dist: black ; extra == 'all'
Requires-Dist: mkdocs (==1.2.1) ; extra == 'all'
Requires-Dist: pdoc3 (==0.9.2) ; extra == 'all'
Requires-Dist: mkdocs-git-snippet (==0.1.1) ; extra == 'all'
Requires-Dist: mkdocs-git-revision-date-localized-plugin (==0.9.2) ; extra == 'all'
Requires-Dist: mkdocs-git-authors-plugin (==0.3.3) ; extra == 'all'
Requires-Dist: mkdocs-rtd-dropdown (==1.0.2) ; extra == 'all'
Requires-Dist: pre-commit (==2.13.0) ; extra == 'all'
Provides-Extra: test
Requires-Dist: pydantic (==1.8.2) ; extra == 'test'
Requires-Dist: fastapi (==0.65.2) ; extra == 'test'
Requires-Dist: uvicorn (==0.11.8) ; extra == 'test'
Requires-Dist: pyparsing (==2.4.7) ; extra == 'test'
Requires-Dist: green (>=2.5.0) ; extra == 'test'
Requires-Dist: coverage ; extra == 'test'
Requires-Dist: mypy ; extra == 'test'
